hdmedians/__init__.py
hdmedians/geomedian.cpython-39-darwin.so
hdmedians/medoid.py
hdmedians/tests/__init__.py
hdmedians/tests/test_geomedian.py
hdmedians/tests/test_medoid.py
hdmedians-0.14.2.dist-info/LICENSE
hdmedians-0.14.2.dist-info/METADATA
hdmedians-0.14.2.dist-info/WHEEL
hdmedians-0.14.2.dist-info/top_level.txt
hdmedians-0.14.2.dist-info/RECORD
