Metadata-Version: 2.1
Name: hdmedians
Version: 0.14.2
Summary: High-dimensional medians
Home-page: http://github.com/daleroberts/hdmedians
Author: Dale Roberts
Author-email: dale.o.roberts@gmail.com
License: Apache License, Version 2.0
Platform: UNKNOWN
Requires-Dist: numpy
Requires-Dist: Cython (>=0.23)
